AIFactoryDS/AbstractProcesses.py
AIFactoryDS/ImageUtilities.py
AIFactoryDS/Worker.py
AIFactoryDS/__init__.py
AIFactoryDS-0.1.13.data/scripts/build_project_skeleton
EasterEggs/__init__.py
EasterEggs/greetings.py
AIFactoryDS-0.1.13.dist-info/METADATA
AIFactoryDS-0.1.13.dist-info/WHEEL
AIFactoryDS-0.1.13.dist-info/top_level.txt
AIFactoryDS-0.1.13.dist-info/RECORD
